e2etest/__init__.py
e2etest/e2e.py
e2etest-0.1.11.dist-info/licenses/LICENSE
e2etest-0.1.11.dist-info/METADATA
e2etest-0.1.11.dist-info/WHEEL
e2etest-0.1.11.dist-info/top_level.txt
e2etest-0.1.11.dist-info/RECORD
